pyfunc_ensembler_runner/__init__.py
pyfunc_ensembler_runner/__main__.py
pyfunc_ensembler_runner/ensembler_runner.py
pyfunc_ensembler_runner/handler.py
pyfunc_ensembler_runner/server.py
tests/__init__.py
tests/conftest.py
tests/test_ensembler_runner.py
turing_pyfunc_ensembler_service-0.16.1rc6.dist-info/METADATA
turing_pyfunc_ensembler_service-0.16.1rc6.dist-info/WHEEL
turing_pyfunc_ensembler_service-0.16.1rc6.dist-info/top_level.txt
turing_pyfunc_ensembler_service-0.16.1rc6.dist-info/RECORD
