Metadata-Version: 2.1
Name: turing-pyfunc-ensembler-service
Version: 0.16.1rc6
Requires-Python: >=3.8,<3.11
Requires-Dist: argparse >=1.4.0
Requires-Dist: cloudpickle ==2.0.0
Requires-Dist: orjson ==3.6.8
Requires-Dist: setuptools <75
Requires-Dist: tornado ==6.1
Requires-Dist: turing-sdk ==v0.16.1-rc6
Provides-Extra: dev
Requires-Dist: black ==22.6.0 ; extra == 'dev'
Requires-Dist: pylint ; extra == 'dev'
Requires-Dist: pytest-cov ; extra == 'dev'
Requires-Dist: pytest <=8.1.2 ; extra == 'dev'
